Metadata-Version: 2.1
Name: demo-same-package-one
Version: 0.0.2
Summary: a test for multi packages on the same namespace
Home-page: UNKNOWN
Author: @muuusiiik
Author-email: muuusiiikd@gmail.com
License: MIT
Platform: UNKNOWN
Classifier: License :: OSI Approved :: MIT License
Classifier: Programming Language :: Python :: 3
Classifier: Programming Language :: Python :: 3.7
Requires-Python: >=3.7
License-File: LICENSE
